music_creatingrhythms/__init__.py
music_creatingrhythms/music_creatingrhythms.py
music_creatingrhythms-0.1.7.dist-info/licenses/LICENSE
music_creatingrhythms-0.1.7.dist-info/METADATA
music_creatingrhythms-0.1.7.dist-info/WHEEL
music_creatingrhythms-0.1.7.dist-info/top_level.txt
music_creatingrhythms-0.1.7.dist-info/RECORD
